CB2325NumericaG2/__init__.py
CB2325NumericaG2/aproximacao/__init__.py
CB2325NumericaG2/aproximacao/ajuste_polinomial_min_quadrados.py
CB2325NumericaG2/aproximacao/minimos_quadrados.py
CB2325NumericaG2/aproximacao/theil_sen.py
CB2325NumericaG2/aproximacao/plotagem/__init__.py
CB2325NumericaG2/aproximacao/plotagem/plot_linear_minimos_quadrados.py
CB2325NumericaG2/aproximacao/plotagem/plot_linear_theil_sen.py
CB2325NumericaG2/aproximacao/plotagem/plot_polinomio_minimos_quadrados.py
CB2325NumericaG2/erros/__init__.py
CB2325NumericaG2/erros/erro_absoluto.py
CB2325NumericaG2/erros/erro_relativo.py
CB2325NumericaG2/integracao/__init__.py
CB2325NumericaG2/integracao/integracao_componentes.py
CB2325NumericaG2/integracao/integracao_retangulo.py
CB2325NumericaG2/integracao/integracao_trapezio.py
CB2325NumericaG2/interpolacao/__init__.py
CB2325NumericaG2/interpolacao/interpolacao_hermite.py
CB2325NumericaG2/interpolacao/interpolacao_polinomial.py
CB2325NumericaG2/interpolacao/linear.py
CB2325NumericaG2/interpolacao/linear_partes.py
CB2325NumericaG2/raizes/__init__.py
CB2325NumericaG2/raizes/bisseccao.py
CB2325NumericaG2/raizes/newton_raphson.py
CB2325NumericaG2/raizes/secante.py
cb2325numericag2-0.1.0.dist-info/licenses/LICENSE
cb2325numericag2-0.1.0.dist-info/METADATA
cb2325numericag2-0.1.0.dist-info/WHEEL
cb2325numericag2-0.1.0.dist-info/top_level.txt
cb2325numericag2-0.1.0.dist-info/RECORD
