Metadata-Version: 2.4
Name: CB2325NumericaG2
Version: 0.1.0
Summary: Biblioteca numérica Python
Author-email: Huann Vicente <al.huann.silva@impatech.edu.br>, Gabriele Ogido <al.gabriela.ogido@impatech.edu.br>, Italo Rennan <al.italo.souza@impatech.edu.br>, Gabrielle <al.gabrielle.silva@impatech.edu.br>, Alan dos Santos <al.alan.santos@impatech.edu.br>, Lucas Silva <al.lucas.silva@impatech.edu.br>, Samuel Bezerra <samuelbezerra411@gmail.com>, Kauã Reichert <al.kaua.reichert@impatech.edu.br>, Daniela <al.daniela.moraes@impatech.edu.br>, Carlos Paulo <al.carlos.paula@impatech.edu.br>, Júlia Q
License: MIT
Project-URL: Homepage, https://github.com/CB2325NumericaG2/CB2325NumericaG2
Project-URL: Repository, https://github.com/CB2325NumericaG2/CB2325NumericaG2.git
Project-URL: Issues, https://github.com/CB2325NumericaG2/CB2325NumericaG2/issues
Requires-Python: >=3.10
License-File: LICENSE
Requires-Dist: numpy
Requires-Dist: sympy
Requires-Dist: matplotlib
Requires-Dist: plotly
Provides-Extra: dev
Requires-Dist: pytest>=7.0; extra == "dev"
Requires-Dist: twine>=4.0.2; extra == "dev"
Dynamic: license-file
